{
  "pt-br":{
    "content": {
      "checklesson": "Marcar aula como concluída",
      "checkedLabelText": "Aula concluída",
      "categoriesTitles": {
        "grammar": "Gramática",
        "vocabulary": "Vocabulário",
        "topics": "Tópicos"
      },
      "levelsDescriptions": {
        "a1": "Iniciante",
        "a2": "Básico",
        "b1": "Intermediário",
        "b2": "Intermediário Superior",
        "c1": "Avançado",
        "c2": "Proficiente"
      },
      "buttons": {
        "previousLesson": "Aula anterior",
        "nextLesson": "Próxima aula"
      }
    },
    "requests": {
      "2.2.1": {"variant": "destructive", "message": "Usuário não está logado. Por favor, realize o login e tente novamente."},
      "2.2.2": {"variant": "destructive", "message": "Valor de verificação inválido. Por favor, entre em contato com o suporte."},
      "2.2.3": {"variant": "destructive", "message": "Erro interno do servidor. Por favor, tente novamente mais tarde."}
    }
  },
  "en-us": {
    "content": {
      "checklesson": "Check lesson as complete",
      "checkedLabelText": "Lesson complete",
      "goBack": "Go back",
      "reportVideoError": "Report video problem",
      "categoriesTitles": {
        "grammar": "Grammar",
        "vocabulary": "Vocabulary",
        "topics": "Topics"
      },
      "levelsDescriptions": {
        "a1": "Beginner",
        "a2": "Basic",
        "b1": "Intermediate",
        "b2": "Upper Intermediate",
        "c1": "Advanced",
        "c2": "Proficient"
      },
      "buttons": {
        "previousLesson": "Previous Lesson",
        "nextLesson": "Next lesson"
      }
    },
    "requests": {
      "2.2.1": {"variant": "destructive", "message": "User is not logged in. Please log in and try again."},
      "2.2.2": {"variant": "destructive", "message": "Invalid check value. Please contact support."},
      "2.2.3": {"variant": "destructive", "message": "Internal server error. Please try again later."}
    }
  }
}